[
  {
    "full_name": "freelensapp/freelens",
    "stargazers_count": 1986,
    "open_issues_count": 104,
    "forks_count": 60
  },
  {
    "full_name": "taishikato/chatsage",
    "stargazers_count": 241,
    "open_issues_count": 1,
    "forks_count": 23
  },
  {
    "full_name": "LiveHelperChat/livehelperchat",
    "stargazers_count": 2071,
    "open_issues_count": 135,
    "forks_count": 711
  },
  {
    "full_name": "OvidijusParsiunas/deep-chat",
    "stargazers_count": 2412,
    "open_issues_count": 28,
    "forks_count": 330
  },
  {
    "full_name": "twentyhq/twenty",
    "stargazers_count": 28200,
    "open_issues_count": 202,
    "forks_count": 3261
  },
  {
    "full_name": "fraunhofer-iem/spha",
    "stargazers_count": 5,
    "open_issues_count": 7,
    "forks_count": 2
  },
  {
    "full_name": "zenangst/KeyboardCowboy",
    "stargazers_count": 1266,
    "open_issues_count": 29,
    "forks_count": 18
  },
  {
    "full_name": "All-Hands-AI/OpenHands",
    "stargazers_count": 57709,
    "open_issues_count": 370,
    "forks_count": 6573
  },
  {
    "full_name": "project-machine/oci-viewer",
    "stargazers_count": 20,
    "open_issues_count": 3,
    "forks_count": 2
  },
  {
    "full_name": "webriots/rate",
    "stargazers_count": 146,
    "open_issues_count": 1,
    "forks_count": 3
  },
  {
    "full_name": "AliRizaAynaci/gorl",
    "stargazers_count": 80,
    "open_issues_count": 0,
    "forks_count": 4
  },
  {
    "full_name": "NilsIrl/dockerc",
    "stargazers_count": 4602,
    "open_issues_count": 26,
    "forks_count": 94
  },
  {
    "full_name": "lmnr-ai/index",
    "stargazers_count": 2262,
    "open_issues_count": 6,
    "forks_count": 117
  },
  {
    "full_name": "imacrayon/alpine-ajax",
    "stargazers_count": 879,
    "open_issues_count": 13,
    "forks_count": 19
  },
  {
    "full_name": "mc256/starlight",
    "stargazers_count": 47,
    "open_issues_count": 11,
    "forks_count": 8
  },
  {
    "full_name": "launchrctl/launchr",
    "stargazers_count": 13,
    "open_issues_count": 20,
    "forks_count": 3
  },
  {
    "full_name": "runabol/tork",
    "stargazers_count": 697,
    "open_issues_count": 13,
    "forks_count": 45
  },
  {
    "full_name": "pgdogdev/pgdog",
    "stargazers_count": 2278,
    "open_issues_count": 33,
    "forks_count": 57
  },
  {
    "full_name": "gimlet-io/capacitor",
    "stargazers_count": 794,
    "open_issues_count": 35,
    "forks_count": 29
  },
  {
    "full_name": "hatchet-dev/hatchet",
    "stargazers_count": 5655,
    "open_issues_count": 73,
    "forks_count": 224
  },
  {
    "full_name": "globallogicuki/provider-harbor",
    "stargazers_count": 5,
    "open_issues_count": 9,
    "forks_count": 5
  },
  {
    "full_name": "k8gb-io/k8gb",
    "stargazers_count": 1038,
    "open_issues_count": 91,
    "forks_count": 111
  },
  {
    "full_name": "docker/model-distribution",
    "stargazers_count": 13,
    "open_issues_count": 4,
    "forks_count": 3
  },
  {
    "full_name": "usertour/usertour",
    "stargazers_count": 1359,
    "open_issues_count": 9,
    "forks_count": 69
  },
  {
    "full_name": "container-registry/harbor-next",
    "stargazers_count": 3,
    "open_issues_count": 19,
    "forks_count": 4
  },
  {
    "full_name": "margo/specification",
    "stargazers_count": 38,
    "open_issues_count": 46,
    "forks_count": 9
  },
  {
    "full_name": "wait4x/wait4x",
    "stargazers_count": 611,
    "open_issues_count": 12,
    "forks_count": 30
  },
  {
    "full_name": "mountain-loop/yaak",
    "stargazers_count": 6713,
    "open_issues_count": 7,
    "forks_count": 219
  },
  {
    "full_name": "uscne/Awesome-European-Tech",
    "stargazers_count": 1118,
    "open_issues_count": 26,
    "forks_count": 79
  },
  {
    "full_name": "asg017/sqlite-vec",
    "stargazers_count": 5729,
    "open_issues_count": 136,
    "forks_count": 212
  }
]